LICENSE
MANIFEST.in
README.rst
setup.py
datasets/__init__.py
datasets/views.py
datasets/templates/datasets/mint.html
datasets/templates/datasets/register.html
doi_site/__init__.py
doi_site/exception.py
doi_site/local_settings.py.ini
doi_site/manage.py
doi_site/settings.py
doi_site/urls.py
doi_site/views.py
doi_site/wsgi.py
doi_site.egg-info/PKG-INFO
doi_site.egg-info/SOURCES.txt
doi_site.egg-info/dependency_links.txt
doi_site.egg-info/requires.txt
doi_site.egg-info/top_level.txt
doi_site/resources/doi_wsgi.conf
doi_site/static/doi_site/css/doi.css
doi_site/static/doi_site/css/stfc/stfc_normalize.css
doi_site/static/doi_site/css/stfc/stfc_print.css
doi_site/static/doi_site/css/stfc/stfc_style.css
doi_site/static/doi_site/images/first.png
doi_site/static/doi_site/images/last.png
doi_site/static/doi_site/images/next.png
doi_site/static/doi_site/images/previous.png
doi_site/static/doi_site/images/stfc/bgUr.png
doi_site/static/doi_site/images/stfc/favicon.ico.png
doi_site/static/doi_site/images/stfc/headerBgEnd.png
doi_site/static/doi_site/images/stfc/headerBgRepeat.png
doi_site/static/doi_site/images/stfc/headerBgStart.png
doi_site/static/doi_site/images/stfc/logoPrint.png
doi_site/static/doi_site/images/stfc/nsci20.png
doi_site/static/doi_site/images/stfc/pf.png
doi_site/static/doi_site/images/stfc/rss.png
doi_site/static/doi_site/images/stfc/stfc.png
doi_site/static/doi_site/images/stfc/stfcLogo.png
doi_site/static/doi_site/images/stfc/twitter.png
doi_site/static/doi_site/images/stfc/youTube.png
doi_site/static/doi_site/scripts/stfc/cookieWarning.js
doi_site/templates/admin/base_site.html
doi_site/templates/doi_site/base.html
doi_site/templates/doi_site/dois.html
doi_site/templates/doi_site/domains.html
doi_site/templates/doi_site/error.html
doi_site/templates/doi_site/index.html
doi_site/templates/doi_site/notes.html
doi_site/templates/doi_site/organisation_wrapper.html
doi_site/templates/doi_site/stfc_skin.html
doi_site/templates/registration/logged_out.html
doi_site/templates/registration/login.html
mds/__init__.py
mds/admin.py
mds/basic_auth.py
mds/models.py
mds/views.py
mds/http/__init__.py
mds/http/delete.py
