Metadata-Version: 1.1
Name: doi-site
Version: 0.2.0
Summary: A simple Django app to wrap datacite calls.
Home-page: http://stfc.ac.uk/
Author: Antony Wilson
Author-email: antony.wilson@stfc.ac.uk
License: BSD License
Platform: UNKNOWN
Classifier: Environment :: Web Environment
Classifier: Framework :: Django
Classifier: Intended Audience :: Developers
Classifier: License :: OSI Approved :: BSD License
Classifier: Operating System :: OS Independent
Classifier: Programming Language :: Python
Classifier: Programming Language :: Python :: 2.7
Classifier: Topic :: Internet :: WWW/HTTP
Classifier: Topic :: Internet :: WWW/HTTP :: Dynamic Content
